ADVfile_manager/__init__.py
ADVfile_manager/core.py
advfile_manager-1.3.2.dist-info/licenses/LICENSE
advfile_manager-1.3.2.dist-info/METADATA
advfile_manager-1.3.2.dist-info/WHEEL
advfile_manager-1.3.2.dist-info/top_level.txt
advfile_manager-1.3.2.dist-info/RECORD
