Metadata-Version: 2.4
Name: ADVfile-manager
Version: 1.3.2
Summary: Unified file abstractions with safe I/O, backups, caching, and async facade for Text/JSON/CSV/YAML/INI/TOML/XML/Excel.
Author: Avi Twil
License: MIT
Project-URL: Homepage, https://github.com/avitwil/ADVfile_manager
Project-URL: Repository, https://github.com/avitwil/ADVfile_manager
Project-URL: Issues, https://github.com/avitwil/ADVfile_manager/issues
Keywords: file-io,json,csv,yaml,ini,toml,xml,excel,backup,async,search,openpyxl,pyyaml,tomli
Classifier: Development Status :: 3 - Alpha
Classifier: Intended Audience :: Developers
Classifier: License :: OSI Approved :: MIT License
Classifier: Programming Language :: Python
Classifier: Programming Language :: Python :: 3
Classifier: Programming Language :: Python :: 3 :: Only
Classifier: Programming Language :: Python :: 3.8
Classifier: Programming Language :: Python :: 3.9
Classifier: Programming Language :: Python :: 3.10
Classifier: Programming Language :: Python :: 3.11
Classifier: Programming Language :: Python :: 3.12
Classifier: Topic :: Software Development :: Libraries
Classifier: Topic :: Utilities
Requires-Python: >=3.8
License-File: LICENSE
Provides-Extra: yaml
Requires-Dist: PyYAML>=6.0; extra == "yaml"
Provides-Extra: toml
Requires-Dist: tomli>=2.0; python_version < "3.11" and extra == "toml"
Requires-Dist: tomli-w>=1.0; extra == "toml"
Provides-Extra: excel
Requires-Dist: openpyxl>=3.1; extra == "excel"
Provides-Extra: all
Requires-Dist: PyYAML>=6.0; extra == "all"
Requires-Dist: tomli>=2.0; python_version < "3.11" and extra == "all"
Requires-Dist: tomli-w>=1.0; extra == "all"
Requires-Dist: openpyxl>=3.1; extra == "all"
Provides-Extra: dev
Requires-Dist: pytest>=8; extra == "dev"
Requires-Dist: pytest-cov>=5; extra == "dev"
Requires-Dist: mypy>=1.10; extra == "dev"
Requires-Dist: ruff>=0.5; extra == "dev"
Requires-Dist: black>=24.0; extra == "dev"
Requires-Dist: types-PyYAML>=6.0.12.20240808; extra == "dev"
Requires-Dist: types-toml>=0.10.8.20240310; extra == "dev"
Dynamic: license-file
